{"start":{"x":-76428,"y":-68001},"commands":[{"direction":"east","steps":22072},{"direction":"north","steps":543},{"direction":"south","steps":21503},{"direction":"west","steps":4549},{"direction":"north","steps":27080},{"direction":"west","steps":13584},{"direction":"west","steps":26640},{"direction":"north","steps":8291},{"direction":"south","steps":27056},{"direction":"east","steps":9172},{"direction":"east","steps":17673},{"direction":"north","steps":2511},{"direction":"east","steps":25767},{"direction":"east","steps":2817},{"direction":"north","steps":32685},{"direction":"north","steps":14287},{"direction":"south","steps":6968},{"direction":"north","steps":18027},{"direction":"south","steps":24254},{"direction":"north","steps":19467},{"direction":"north","steps":2377},{"direction":"north","steps":8890},{"direction":"west","steps":24565},{"direction":"west","steps":8224},{"direction":"east","steps":18978},{"direction":"north","steps":10797},{"direction":"east","steps":205},{"direction":"east","steps":20644},{"direction":"west","steps":7618},{"direction":"north","steps":23390},{"direction":"west","steps":7874},{"direction":"east","steps":7633},{"direction":"east","steps":25454},{"direction":"east","steps":19140},{"direction":"north","steps":22884},{"direction":"east","steps":1696},{"direction":"east","steps":6298},{"direction":"west","steps":16078},{"direction":"south","steps":22084},{"direction":"north","steps":31906},{"direction":"north","steps":655},{"direction":"south","steps":3289},{"direction":"north","steps":23873},{"direction":"west","steps":32617},{"direction":"west","steps":5806},{"direction":"south","steps":8914},{"direction":"north","steps":547},{"direction":"west","steps":1840},{"direction":"north","steps":18179},{"direction":"west","steps":12047},{"direction":"south","steps":13077},{"direction":"south","steps":19394},{"direction":"east","steps":27614},{"direction":"north","steps":2507},{"direction":"west","steps":30148},{"direction":"north","steps":18576},{"direction":"south","steps":21236},{"direction":"east","steps":7186},{"direction":"south","steps":10960},{"direction":"east","steps":30972},{"direction":"north","steps":21052},{"direction":"east","steps":18454},{"direction":"north","steps":9868},{"direction":"north","steps":16058},{"direction":"west","steps":17091},{"direction":"east","steps":15106},{"direction":"south","steps":2939},{"direction":"west","steps":4527},{"direction":"west","steps":3705},{"direction":"west","steps":30549},{"direction":"east","steps":17260},{"direction":"west","steps":14126},{"direction":"south","steps":28043},{"direction":"south","steps":17903},{"direction":"east","steps":3305},{"direction":"west","steps":7005},{"direction":"north","steps":14817},{"direction":"west","steps":18109},{"direction":"east","steps":8552},{"direction":"east","steps":24374},{"direction":"north","steps":2823},{"direction":"south","steps":4201},{"direction":"south","steps":30398},{"direction":"west","steps":20760},{"direction":"south","steps":8883},{"direction":"south","steps":578},{"direction":"south","steps":8352},{"direction":"west","steps":27845},{"direction":"south","steps":25344},{"direction":"south","steps":9809},{"direction":"west","steps":10598},{"direction":"north","steps":30537},{"direction":"east","steps":15645},{"direction":"west","steps":10487},{"direction":"west","steps":11623},{"direction":"east","steps":16580},{"direction":"north","steps":29079},{"direction":"east","steps":12553},{"direction":"north","steps":333},{"direction":"east","steps":15272},{"direction":"west","steps":97},{"direction":"south","steps":1415},{"direction":"west","steps":1052},{"direction":"east","steps":7036},{"direction":"south","steps":27205},{"direction":"east","steps":5367},{"direction":"west","steps":31992},{"direction":"north","steps":31602},{"direction":"east","steps":30707},{"direction":"west","steps":9832},{"direction":"south","steps":32393},{"direction":"south","steps":9318},{"direction":"east","steps":23274},{"direction":"south","steps":12506},{"direction":"west","steps":10203},{"direction":"west","steps":8693},{"direction":"east","steps":639},{"direction":"east","steps":19934},{"direction":"east","steps":6402},{"direction":"south","steps":14431},{"direction":"east","steps":15244},{"direction":"south","steps":21579},{"direction":"south","steps":25364},{"direction":"south","steps":6734},{"direction":"west","steps":27779},{"direction":"east","steps":22391},{"direction":"north","steps":22222},{"direction":"west","steps":18384},{"direction":"west","steps":18194},{"direction":"north","steps":20073},{"direction":"south","steps":25266},{"direction":"west","steps":15135},{"direction":"south","steps":19927},{"direction":"north","steps":12402},{"direction":"west","steps":20645},{"direction":"north","steps":9506},{"direction":"north","steps":7997},{"direction":"south","steps":7720},{"direction":"east","steps":15612},{"direction":"south","steps":14895},{"direction":"west","steps":25088},{"direction":"east","steps":32571},{"direction":"west","steps":22599},{"direction":"north","steps":30447},{"direction":"north","steps":31191},{"direction":"east","steps":22965},{"direction":"south","steps":15913},{"direction":"north","steps":16285},{"direction":"west","steps":14073},{"direction":"south","steps":19805},{"direction":"west","steps":24180},{"direction":"north","steps":1141},{"direction":"east","steps":18514},{"direction":"west","steps":7947},{"direction":"south","steps":30555},{"direction":"north","steps":26599},{"direction":"east","steps":19635},{"direction":"east","steps":24385},{"direction":"east","steps":1080},{"direction":"east","steps":6676},{"direction":"north","steps":2104},{"direction":"east","steps":9760},{"direction":"north","steps":20875},{"direction":"north","steps":12991},{"direction":"west","steps":6264},{"direction":"east","steps":5689},{"direction":"east","steps":5105},{"direction":"north","steps":30848},{"direction":"north","steps":8931},{"direction":"west","steps":31214},{"direction":"south","steps":3601},{"direction":"north","steps":22743},{"direction":"east","steps":23956},{"direction":"west","steps":29970},{"direction":"west","steps":8232},{"direction":"west","steps":14492},{"direction":"south","steps":23157},{"direction":"south","steps":31593},{"direction":"north","steps":14641},{"direction":"west","steps":10873},{"direction":"east","steps":19880},{"direction":"north","steps":3025},{"direction":"west","steps":23267},{"direction":"north","steps":14264},{"direction":"east","steps":32595},{"direction":"west","steps":22385},{"direction":"north","steps":4394},{"direction":"west","steps":3852},{"direction":"south","steps":20777},{"direction":"south","steps":2540},{"direction":"south","steps":5357},{"direction":"east","steps":7901},{"direction":"east","steps":30102},{"direction":"west","steps":19210},{"direction":"west","steps":20660},{"direction":"east","steps":27347},{"direction":"south","steps":24528},{"direction":"south","steps":27363},{"direction":"south","steps":17281},{"direction":"south","steps":28065},{"direction":"west","steps":18820},{"direction":"north","steps":13885},{"direction":"north","steps":7815},{"direction":"south","steps":8736},{"direction":"west","steps":6898},{"direction":"east","steps":21027},{"direction":"north","steps":24041},{"direction":"east","steps":18082},{"direction":"east","steps":24180},{"direction":"south","steps":24752},{"direction":"east","steps":4017},{"direction":"east","steps":26713},{"direction":"east","steps":32497},{"direction":"east","steps":22855},{"direction":"east","steps":7630},{"direction":"north","steps":30443},{"direction":"north","steps":16796},{"direction":"east","steps":1108},{"direction":"north","steps":15226},{"direction":"west","steps":16009},{"direction":"south","steps":11316},{"direction":"west","steps":23228},{"direction":"north","steps":12522},{"direction":"south","steps":11973},{"direction":"south","steps":23513},{"direction":"west","steps":3461},{"direction":"east","steps":15374},{"direction":"south","steps":32142},{"direction":"east","steps":30084},{"direction":"east","steps":14752},{"direction":"north","steps":7397},{"direction":"east","steps":10133},{"direction":"north","steps":32007},{"direction":"north","steps":25236},{"direction":"west","steps":17047},{"direction":"north","steps":969},{"direction":"east","steps":1877},{"direction":"east","steps":16360},{"direction":"south","steps":21230},{"direction":"south","steps":29081},{"direction":"north","steps":24435},{"direction":"east","steps":3054},{"direction":"north","steps":5867},{"direction":"north","steps":19224},{"direction":"west","steps":19533},{"direction":"south","steps":23903},{"direction":"east","steps":18032},{"direction":"west","steps":18240},{"direction":"north","steps":6421},{"direction":"south","steps":2326},{"direction":"north","steps":16844},{"direction":"west","steps":3475},{"direction":"south","steps":6559},{"direction":"north","steps":21616},{"direction":"west","steps":1266},{"direction":"west","steps":29912},{"direction":"west","steps":19252},{"direction":"north","steps":12278},{"direction":"north","steps":24565},{"direction":"east","steps":4965},{"direction":"north","steps":20600},{"direction":"east","steps":18428},{"direction":"north","steps":20761},{"direction":"east","steps":19534},{"direction":"south","steps":9575},{"direction":"south","steps":3995},{"direction":"west","steps":11671},{"direction":"east","steps":20468},{"direction":"east","steps":17480},{"direction":"south","steps":16827},{"direction":"west","steps":9736},{"direction":"east","steps":10668},{"direction":"south","steps":17030},{"direction":"west","steps":25028},{"direction":"west","steps":21441},{"direction":"north","steps":16051},{"direction":"south","steps":4043},{"direction":"east","steps":31029},{"direction":"north","steps":11159},{"direction":"south","steps":14707},{"direction":"south","steps":4145},{"direction":"east","steps":3291},{"direction":"west","steps":11004},{"direction":"south","steps":5760},{"direction":"south","steps":16583},{"direction":"north","steps":23053},{"direction":"east","steps":25465},{"direction":"north","steps":22300},{"direction":"north","steps":16671},{"direction":"south","steps":10591},{"direction":"west","steps":32671},{"direction":"west","steps":25167},{"direction":"north","steps":20701},{"direction":"west","steps":7025},{"direction":"west","steps":23220},{"direction":"south","steps":23994},{"direction":"south","steps":17061},{"direction":"west","steps":3032},{"direction":"north","steps":13429},{"direction":"east","steps":13552},{"direction":"north","steps":28531},{"direction":"north","steps":5909},{"direction":"south","steps":14359},{"direction":"south","steps":12980},{"direction":"west","steps":29418},{"direction":"west","steps":24648},{"direction":"south","steps":6850},{"direction":"west","steps":17806},{"direction":"east","steps":8081},{"direction":"north","steps":2730},{"direction":"east","steps":19807},{"direction":"north","steps":27},{"direction":"south","steps":22470},{"direction":"north","steps":30298},{"direction":"west","steps":1208},{"direction":"south","steps":20231},{"direction":"east","steps":15526},{"direction":"south","steps":4863},{"direction":"south","steps":635},{"direction":"north","steps":7518},{"direction":"north","steps":14434},{"direction":"south","steps":8515},{"direction":"west","steps":8862},{"direction":"south","steps":14806},{"direction":"north","steps":14197},{"direction":"north","steps":928},{"direction":"south","steps":5821},{"direction":"west","steps":14547},{"direction":"north","steps":25538},{"direction":"east","steps":30445},{"direction":"west","steps":32759},{"direction":"east","steps":25483},{"direction":"north","steps":3766},{"direction":"north","steps":1618},{"direction":"south","steps":32495},{"direction":"south","steps":16306},{"direction":"south","steps":15991},{"direction":"south","steps":17758},{"direction":"south","steps":18218},{"direction":"north","steps":24769},{"direction":"north","steps":19977},{"direction":"west","steps":30470},{"direction":"south","steps":15625},{"direction":"south","steps":29529},{"direction":"west","steps":13693},{"direction":"west","steps":12841},{"direction":"south","steps":5447},{"direction":"north","steps":5159},{"direction":"north","steps":31853},{"direction":"south","steps":19364},{"direction":"east","steps":30260},{"direction":"east","steps":23941},{"direction":"east","steps":16894},{"direction":"north","steps":32392},{"direction":"east","steps":30521},{"direction":"south","steps":11674},{"direction":"north","steps":8020},{"direction":"west","steps":13059},{"direction":"west","steps":30380},{"direction":"north","steps":3442}]}
